pyjosa/__init__.py
pyjosa/exceptions.py
pyjosa/jonsung.py
pyjosa/josa.py
pyjosa/test.py
pyjosa-1.0.3.dist-info/LICENSE
pyjosa-1.0.3.dist-info/METADATA
pyjosa-1.0.3.dist-info/WHEEL
pyjosa-1.0.3.dist-info/top_level.txt
pyjosa-1.0.3.dist-info/RECORD
