Metadata-Version: 2.1
Name: pyjosa
Version: 1.0.3
Summary: 한국어 조사 처리 패키지
Home-page: https://github.com/kimsehwan96/pyjosa
Author: sehwan.kim
Author-email: sehwan.kim@ingkle.com
License: MIT
Platform: UNKNOWN
Classifier: Programming Language :: Python :: 3.7
License-File: LICENSE
